CHANGELOG.rst
LICENSE
MANIFEST.in
README.rst
setup.py
django_u2f/__init__.py
django_u2f/admin.py
django_u2f/apps.py
django_u2f/forms.py
django_u2f/models.py
django_u2f/oath.py
django_u2f/urls.py
django_u2f/views.py
django_u2f.egg-info/PKG-INFO
django_u2f.egg-info/SOURCES.txt
django_u2f.egg-info/dependency_links.txt
django_u2f.egg-info/requires.txt
django_u2f.egg-info/top_level.txt
django_u2f/management/__init__.py
django_u2f/management/commands/__init__.py
django_u2f/management/commands/addbackupcode.py
django_u2f/migrations/0001_initial.py
django_u2f/migrations/0002_add_backup_codes.py
django_u2f/migrations/0003_add_totp.py
django_u2f/migrations/0004_auto_20170425_1557.py
django_u2f/migrations/__init__.py
django_u2f/static/django_u2f/django_u2f.js
django_u2f/templates/u2f/add_key.html
django_u2f/templates/u2f/backup_codes.html
django_u2f/templates/u2f/base.html
django_u2f/templates/u2f/key_list.html
django_u2f/templates/u2f/login.html
django_u2f/templates/u2f/totp_device.html
django_u2f/templates/u2f/totpdevice_list.html
django_u2f/templates/u2f/two_factor_settings.html
django_u2f/templates/u2f/verify_second_factor.html