Metadata-Version: 2.1
Name: django-u2f
Version: 1.0.1
Summary: FIDO U2F security token support for Django
Home-page: https://github.com/gavinwahl/django-u2f
Author: Gavin Wahl
Author-email: gavinwahl@gmail.com
License: BSD
Classifier: Environment :: Web Environment
Classifier: Framework :: Django
Classifier: Intended Audience :: Developers
Classifier: License :: OSI Approved :: BSD License
Classifier: Programming Language :: Python :: 2.7
Classifier: Programming Language :: Python :: 3.4
Classifier: Programming Language :: Python :: 3.5
Classifier: Topic :: Security
Classifier: Topic :: Security :: Cryptography
License-File: LICENSE
